{
	"format_version": "1.8.0",
	"animations": {
		"timestop": {
			"animation_length": 1.5417,
			"bones": {
				"body": {
					"position": {
						"0.0": {
							"vector": [0, 0, 0]
						},
						"0.2083": {
							"vector": [0, -2.2, 1.1],
							"easing": "easeOutBack"
						},
						"0.4167": {
							"vector": [0, 4.5, 0],
							"easing": "easeOutBack"
						},
						"1.125": {
							"vector": [0, 0, 0],
							"easing": "easeOutBack"
						},
						"1.5": {
							"vector": [0, 0, 0]
						}
					}
				},
				"right_arm": {
					"rotation": {
						"0.0": {
							"vector": [0, 0, 0]
						},
						"0.25": {
							"vector": [-90, -58.75, 20],
							"easing": "easeOutBack"
						},
						"0.7083": {
							"vector": [0, 25, 80],
							"easing": "easeOutBack"
						},
						"1.5": {
							"vector": [0, 0, 0],
							"easing": "easeOutBack"
						}
					}
				},
				"left_arm": {
					"rotation": {
						"0.0": {
							"vector": [0, 0, 0]
						},
						"0.25": {
							"vector": [-41.77075, 55.03063, 7.73634],
							"easing": "easeOutBack"
						},
						"0.7083": {
							"vector": [0, -25, -72.5],
							"easing": "easeOutBack"
						},
						"1.5": {
							"vector": [0, 0, 0],
							"easing": "easeOutBack"
						}
					}
				},
				"right_leg": {
					"position": {
						"0.0": {
							"vector": [0, 0, 0]
						},
						"0.2083": {
							"vector": [0, 2.3, -4],
							"easing": "easeOutBack"
						},
						"0.4167": {
							"vector": [0, -0.7, 0],
							"easing": "easeOutBack"
						},
						"1.125": {
							"vector": [0, 0, 0],
							"easing": "easeOutBack"
						}
					}
				},
				"left_leg": {
					"rotation": {
						"0.0": {
							"vector": [0, 0, 0]
						},
						"0.2083": {
							"vector": [37.5, 0, 0],
							"easing": "easeOutBack"
						},
						"0.4167": {
							"vector": [52.5, 0, 0],
							"easing": "easeOutBack"
						},
						"1.125": {
							"vector": [0, 0, 0],
							"easing": "easeOutBack"
						}
					},
					"position": {
						"0.0": {
							"vector": [0, 0, 0]
						},
						"0.2083": {
							"vector": [0, 0, -4]
						},
						"0.4167": {
							"vector": [0, 2, -5.09]
						},
						"1.125": {
							"vector": [0, 0, 0]
						}
					}
				}
			}
		}
	},
	"geckolib_format_version": 2
}